__init__.py
cli.py
run_service.py
api/__init__.py
api/client.py
api/endpoints.py
api/static/.gitkeep
api/templates/index.html
ml/__init__.py
ml/huggingface.py
ml/mlflow.py
ml/train.py
ml/upload_model.py
schema/__init__.py
schema/schema.py
intent_service-0.1.10.dist-info/LICENSE
intent_service-0.1.10.dist-info/METADATA
intent_service-0.1.10.dist-info/WHEEL
intent_service-0.1.10.dist-info/entry_points.txt
intent_service-0.1.10.dist-info/top_level.txt
intent_service-0.1.10.dist-info/RECORD
