Metadata-Version: 2.1
Name: intent-service
Version: 0.1.10
Summary: Intent classification service
Author-email: Eliot Zubkoff <eliot.i.zubkoff@gmail.com>
License: MIT
Project-URL: homepage, https://github.com/eliotdoesprogramming/intent-service
Project-URL: repository, https://github.com/eliotdoesprogramming/intent-service
Keywords: intent,classification,nlp,machine-learning
Classifier: Development Status :: 4 - Beta
Classifier: Intended Audience :: Developers
Classifier: License :: OSI Approved :: MIT License
Classifier: Programming Language :: Python :: 3
Classifier: Programming Language :: Python :: 3.10
Classifier: Topic :: Scientific/Engineering :: Artificial Intelligence
Requires-Python: >=3.10
License-File: LICENSE
Requires-Dist: fastapi<1.0.0,>=0.68.0
Requires-Dist: pydantic<3.0.0,>=2.4.2
Requires-Dist: mlflow>=2.18.0
Requires-Dist: polars>=0.20.0
Requires-Dist: uvicorn>=0.15.0
Requires-Dist: requests==2.31.0
Requires-Dist: python-multipart==0.0.6
Requires-Dist: httpx>=0.27.2
Requires-Dist: torch>=2.5.1
Requires-Dist: transformers>=4.46.3
Requires-Dist: typer>=0.9.0
Requires-Dist: rich>=13.7.0
Requires-Dist: jinja2>=3.1.4
